kcmt/__init__.py
kcmt/_optional.py
kcmt/benchmark.py
kcmt/cli.py
kcmt/commit.py
kcmt/config.py
kcmt/core.py
kcmt/exceptions.py
kcmt/git.py
kcmt/ink_backend.py
kcmt/legacy_cli.py
kcmt/llm.py
kcmt/main.py
kcmt/providers/anthropic_driver.py
kcmt/providers/base.py
kcmt/providers/openai_driver.py
kcmt/providers/pricing.py
kcmt/providers/xai_driver.py
kcmt/ui/__init__.py
kcmt/ui/ink/__init__.py
kcmt/ui/ink/index.mjs
kcmt/ui/ink/package.json
kcmt/ui/ink/src/app-context.mjs
kcmt/ui/ink/src/app.mjs
kcmt/ui/ink/src/backend-client.mjs
kcmt/ui/ink/src/components/benchmark-view.mjs
kcmt/ui/ink/src/components/configure-view.mjs
kcmt/ui/ink/src/components/main-menu.mjs
kcmt/ui/ink/src/components/workflow-view.mjs
kcmt-0.3.1.dist-info/METADATA
kcmt-0.3.1.dist-info/WHEEL
kcmt-0.3.1.dist-info/entry_points.txt
kcmt-0.3.1.dist-info/licenses/LICENSE
kcmt-0.3.1.dist-info/RECORD
