Metadata-Version: 2.4
Name: kcmt
Version: 0.3.1
Summary: AI-powered atomic Git staging and committing tool with LLM-generated conventional commits
Project-URL: Homepage, https://github.com/djh00t/kcmt
Project-URL: Repository, https://github.com/djh00t/kcmt
Project-URL: Issues, https://github.com/djh00t/kcmt/issues
Author-email: David Hooton <david@hooton.org>
License: MIT License
License-File: LICENSE
Keywords: LLM,OpenAI,cli,commit,conventional commits,developer-tools,git
Classifier: Development Status :: 3 - Alpha
Classifier: Environment :: Console
Classifier: Intended Audience :: Developers
Classifier: License :: OSI Approved :: MIT License
Classifier: Programming Language :: Python
Classifier: Programming Language :: Python :: 3
Classifier: Programming Language :: Python :: 3.12
Classifier: Programming Language :: Python :: 3.13
Classifier: Topic :: Software Development :: Build Tools
Classifier: Topic :: Software Development :: Version Control :: Git
Requires-Python: >=3.12
Requires-Dist: genai-prices>=0.0.42
Requires-Dist: httpx[http2]>=0.28.1
Requires-Dist: openai>=2.8.1
Provides-Extra: dev
Requires-Dist: black>=25.11.0; extra == 'dev'
Requires-Dist: build>=1.3.0; extra == 'dev'
Requires-Dist: iniconfig>=2.3.0; extra == 'dev'
Requires-Dist: isort>=7.0.0; extra == 'dev'
Requires-Dist: mypy>=1.18.2; extra == 'dev'
Requires-Dist: pytest-bdd>=8.1.0; extra == 'dev'
Requires-Dist: pytest-cov>=7.0.0; extra == 'dev'
Requires-Dist: pytest-xdist>=3.8.0; extra == 'dev'
Requires-Dist: pytest>=9.0.1; extra == 'dev'
Requires-Dist: ruff>=0.14.5; extra == 'dev'
Requires-Dist: twine>=6.2.0; extra == 'dev'
